test_first/DSL.py
test_first/__init__.py
test_first/argumentexpectations.py
test_first/call_character.py
test_first/call_formatter.py
test_first/call_modifiers/__init__.py
test_first/call_modifiers/asynchronous.py
test_first/call_modifiers/awaitable.py
test_first/call_modifiers/base.py
test_first/call_modifiers/synchronous.py
test_first/call_modifiers/trivial.py
test_first/expectationmaker.py
test_first/expectations/__init__.py
test_first/expectations/call.py
test_first/failhooks.py
test_first/fake.py
test_first/fake_privacy_violator.py
test_first/fakefile.py
test_first/fakeobject.py
test_first/frequentlyused.py
test_first/hook.py
test_first/patch_module.py
test_first/saveargument.py
test_first/scenario.py
test_first/scenario_mocks.py
test_first/test_first_exception.py
test_first-8.0.1.dist-info/LICENSE
test_first-8.0.1.dist-info/WHEEL
test_first-8.0.1.dist-info/METADATA
test_first-8.0.1.dist-info/RECORD
