Metadata-Version: 2.1
Name: test-first
Version: 8.0.1
Summary: Test First Python Mocking Framework designed especially for TDD
License: MIT
Author: Yoav Kleinberger
Author-email: haarcuba@gmail.com
Requires-Python: >=3.8,<4.0
Classifier: Intended Audience :: Developers
Classifier: License :: OSI Approved :: MIT License
Classifier: Operating System :: OS Independent
Classifier: Programming Language :: Python
Classifier: Programming Language :: Python :: 3
Classifier: Programming Language :: Python :: 3.8
Classifier: Programming Language :: Python :: 3.9
Classifier: Topic :: Software Development :: Testing
Requires-Dist: pytest (>=6.2.5,<7.0.0)
